pymultieis/__init__.py
pymultieis/multieis.py
pymultieis-0.1.1.dist-info/LICENSE.md
pymultieis-0.1.1.dist-info/WHEEL
pymultieis-0.1.1.dist-info/METADATA
pymultieis-0.1.1.dist-info/RECORD
