Metadata-Version: 2.1
Name: pymultieis
Version: 0.1.1
Summary: A library for fitting a sequence of electrochemical impedance spectra.
Home-page: https://github.com/richinex/pymultieis
License: MIT
Keywords: electrochemical impedance spectroscopy, eis, batch fitting, multiple spectra, torch
Author: Richard Chukwu
Author-email: richinex@gmail.com
Maintainer: Richard Chukwu
Maintainer-email: richinex@gmail.com
Requires-Python: >=3.9,<3.10
Classifier: Intended Audience :: Science/Research
Classifier: License :: OSI Approved :: MIT License
Classifier: Operating System :: OS Independent
Classifier: Programming Language :: Python :: 3
Classifier: Programming Language :: Python :: 3.10
Classifier: Programming Language :: Python :: 3.9
Provides-Extra: docs
Requires-Dist: matplotlib (==3.5)
Requires-Dist: numpy (==1.23.1)
Requires-Dist: pandas (>=1.4.4,<2.0.0)
Requires-Dist: pytorch-minimize (>=0.0.2,<0.0.3)
Requires-Dist: scipy (==1.9.3)
Requires-Dist: torch (>=1.13.0,<2.0.0)
Project-URL: Documentation, https://pymultieis.readthedocs.io/en/latest/index.html
Project-URL: Repository, https://github.com/richinex/pymultieis
